{"schema_version":1,"dates":["2026-07-22","2026-07-23"],"issues":{"8101":{"yushi_zan":[3000,1700],"kashikabu_zan":[100,0],"sashihiki_zan":[2900,1700],"yushi_shin":[0,0],"yushi_hen":[300,1300],"kashikabu_shin":[0,0],"kashikabu_hen":[0,100]},"8103":{"yushi_zan":[27400,27300],"kashikabu_zan":[0,100],"sashihiki_zan":[27400,27200],"yushi_shin":[900,200],"yushi_hen":[0,300],"kashikabu_shin":[0,100],"kashikabu_hen":[100,0]},"8104":{"yushi_zan":[9900,10000],"kashikabu_zan":[0,0],"sashihiki_zan":[9900,10000],"yushi_shin":[100,100],"yushi_hen":[100,0],"kashikabu_shin":[0,0],"kashikabu_hen":[0,0]},"8105":{"yushi_zan":[381200,368500],"kashikabu_zan":[0,0],"sashihiki_zan":[381200,368500],"yushi_shin":[23500,800],"yushi_hen":[4700,13500],"kashikabu_shin":[0,0],"kashikabu_hen":[0,0]},"8107":{"yushi_zan":[38800,27000],"kashikabu_zan":[0,0],"sashihiki_zan":[38800,27000],"yushi_shin":[200,0],"yushi_hen":[0,11800],"kashikabu_shin":[0,0],"kashikabu_hen":[0,0]},"8111":{"yushi_zan":[21400,21300],"kashikabu_zan":[13900,12700],"sashihiki_zan":[7500,8600],"yushi_shin":[2100,0],"yushi_hen":[0,100],"kashikabu_shin":[0,0],"kashikabu_hen":[2000,1200]},"8113":{"yushi_zan":[107900,117100],"kashikabu_zan":[100,100],"sashihiki_zan":[107800,117000],"yushi_shin":[10900,9200],"yushi_hen":[0,0],"kashikabu_shin":[0,0],"kashikabu_hen":[0,0]},"8115":{"yushi_zan":[1800,1800],"kashikabu_zan":[0,0],"sashihiki_zan":[1800,1800],"yushi_shin":[100,100],"yushi_hen":[100,100],"kashikabu_shin":[0,0],"kashikabu_hen":[0,0]},"8117":{"yushi_zan":[17800,17600],"kashikabu_zan":[17800,17600],"sashihiki_zan":[0,0],"yushi_shin":[0,2100],"yushi_hen":[1100,2300],"kashikabu_shin":[0,200],"kashikabu_hen":[1100,400]},"8118":{"yushi_zan":[2600,2600],"kashikabu_zan":[8400,8700],"sashihiki_zan":[-5800,-6100],"yushi_shin":[0,0],"yushi_hen":[100,0],"kashikabu_shin":[0,300],"kashikabu_hen":[600,0]},"8119":{"yushi_zan":[0,0],"kashikabu_zan":[0,0],"sashihiki_zan":[0,0],"yushi_shin":[0,0],"yushi_hen":[0,0],"kashikabu_shin":[0,0],"kashikabu_hen":[0,0]},"8123":{"yushi_zan":[0,0],"kashikabu_zan":[0,0],"sashihiki_zan":[0,0],"yushi_shin":[0,0],"yushi_hen":[0,0],"kashikabu_shin":[0,0],"kashikabu_hen":[0,0]},"8125":{"yushi_zan":[20800,20700],"kashikabu_zan":[20800,20700],"sashihiki_zan":[0,0],"yushi_shin":[0,100],"yushi_hen":[500,200],"kashikabu_shin":[200,200],"kashikabu_hen":[700,300]},"8127":{"yushi_zan":[5100,5100],"kashikabu_zan":[30000,27100],"sashihiki_zan":[-24900,-22000],"yushi_shin":[100,200],"yushi_hen":[200,200],"kashikabu_shin":[12800,0],"kashikabu_hen":[0,2900]},"8129":{"yushi_zan":[1100,1100],"kashikabu_zan":[0,0],"sashihiki_zan":[1100,1100],"yushi_shin":[100,0],"yushi_hen":[0,0],"kashikabu_shin":[0,0],"kashikabu_hen":[0,0]},"8130":{"yushi_zan":[18900,20200],"kashikabu_zan":[18900,20200],"sashihiki_zan":[0,0],"yushi_shin":[1600,1300],"yushi_hen":[0,0],"kashikabu_shin":[1600,1300],"kashikabu_hen":[0,0]},"8131":{"yushi_zan":[8700,9000],"kashikabu_zan":[107700,104900],"sashihiki_zan":[-99000,-95900],"yushi_shin":[100,300],"yushi_hen":[100,0],"kashikabu_shin":[1000,0],"kashikabu_hen":[100,2800]},"8132":{"yushi_zan":[900,1000],"kashikabu_zan":[18800,18700],"sashihiki_zan":[-17900,-17700],"yushi_shin":[200,100],"yushi_hen":[0,0],"kashikabu_shin":[0,0],"kashikabu_hen":[300,100]},"8133":{"yushi_zan":[20500,23000],"kashikabu_zan":[72700,66600],"sashihiki_zan":[-52200,-43600],"yushi_shin":[0,2500],"yushi_hen":[700,0],"kashikabu_shin":[1300,2000],"kashikabu_hen":[0,8100]},"8135":{"yushi_zan":[32100,32100],"kashikabu_zan":[0,0],"sashihiki_zan":[32100,32100],"yushi_shin":[0,0],"yushi_hen":[0,0],"kashikabu_shin":[0,0],"kashikabu_hen":[0,0]},"8136":{"yushi_zan":[1722900,1663200],"kashikabu_zan":[28000,30000],"sashihiki_zan":[1694900,1633200],"yushi_shin":[196000,21600],"yushi_hen":[1301400,81300],"kashikabu_shin":[0,2000],"kashikabu_hen":[100,0]},"8137":{"yushi_zan":[14800,14400],"kashikabu_zan":[3000,3000],"sashihiki_zan":[11800,11400],"yushi_shin":[100,100],"yushi_hen":[0,500],"kashikabu_shin":[200,0],"kashikabu_hen":[0,0]},"8138":{"yushi_zan":[0,0],"kashikabu_zan":[0,0],"sashihiki_zan":[0,0],"yushi_shin":[0,0],"yushi_hen":[0,0],"kashikabu_shin":[0,0],"kashikabu_hen":[0,0]},"8139":{"yushi_zan":[125000,125000],"kashikabu_zan":[0,0],"sashihiki_zan":[125000,125000],"yushi_shin":[1100,0],"yushi_hen":[0,0],"kashikabu_shin":[0,0],"kashikabu_hen":[0,0]},"8141":{"yushi_zan":[8800,8800],"kashikabu_zan":[8800,8800],"sashihiki_zan":[0,0],"yushi_shin":[0,0],"yushi_hen":[0,0],"kashikabu_shin":[0,0],"kashikabu_hen":[0,0]},"8142":{"yushi_zan":[10600,9200],"kashikabu_zan":[10600,9200],"sashihiki_zan":[0,0],"yushi_shin":[2000,600],"yushi_hen":[300,2000],"kashikabu_shin":[1900,400],"kashikabu_hen":[200,1800]},"8143":{"yushi_zan":[800,800],"kashikabu_zan":[0,0],"sashihiki_zan":[800,800],"yushi_shin":[0,0],"yushi_hen":[100,0],"kashikabu_shin":[0,0],"kashikabu_hen":[0,0]},"8144":{"yushi_zan":[0,100],"kashikabu_zan":[0,0],"sashihiki_zan":[0,100],"yushi_shin":[0,100],"yushi_hen":[0,0],"kashikabu_shin":[0,0],"kashikabu_hen":[0,0]},"8147":{"yushi_zan":[0,0],"kashikabu_zan":[0,0],"sashihiki_zan":[0,0],"yushi_shin":[0,0],"yushi_hen":[0,0],"kashikabu_shin":[0,0],"kashikabu_hen":[0,0]},"8150":{"yushi_zan":[11200,13200],"kashikabu_zan":[0,0],"sashihiki_zan":[11200,13200],"yushi_shin":[2000,2000],"yushi_hen":[0,0],"kashikabu_shin":[0,0],"kashikabu_hen":[100,0]},"8151":{"yushi_zan":[91500,91500],"kashikabu_zan":[75500,73100],"sashihiki_zan":[16000,18400],"yushi_shin":[0,300],"yushi_hen":[2500,300],"kashikabu_shin":[3500,0],"kashikabu_hen":[0,2400]},"8152":{"yushi_zan":[3000,3000],"kashikabu_zan":[0,0],"sashihiki_zan":[3000,3000],"yushi_shin":[0,0],"yushi_hen":[0,0],"kashikabu_shin":[0,0],"kashikabu_hen":[0,0]},"8153":{"yushi_zan":[12400,13300],"kashikabu_zan":[56300,58300],"sashihiki_zan":[-43900,-45000],"yushi_shin":[300,900],"yushi_hen":[100,0],"kashikabu_shin":[3500,2200],"kashikabu_hen":[100,200]},"8154":{"yushi_zan":[6700,6800],"kashikabu_zan":[6700,6800],"sashihiki_zan":[0,0],"yushi_shin":[1200,200],"yushi_hen":[1600,100],"kashikabu_shin":[100,100],"kashikabu_hen":[100,0]},"8157":{"yushi_zan":[200,200],"kashikabu_zan":[200,200],"sashihiki_zan":[0,0],"yushi_shin":[100,0],"yushi_hen":[0,0],"kashikabu_shin":[100,0],"kashikabu_hen":[0,0]},"8158":{"yushi_zan":[3500,3600],"kashikabu_zan":[6400,6200],"sashihiki_zan":[-2900,-2600],"yushi_shin":[300,100],"yushi_hen":[0,0],"kashikabu_shin":[0,0],"kashikabu_hen":[0,200]},"8159":{"yushi_zan":[2100,2000],"kashikabu_zan":[500,400],"sashihiki_zan":[1600,1600],"yushi_shin":[100,0],"yushi_hen":[100,100],"kashikabu_shin":[200,200],"kashikabu_hen":[100,300]},"8160":{"yushi_zan":[17200,17100],"kashikabu_zan":[60900,62200],"sashihiki_zan":[-43700,-45100],"yushi_shin":[600,600],"yushi_hen":[100,700],"kashikabu_shin":[11700,1300],"kashikabu_hen":[0,0]},"8163":{"yushi_zan":[14700,14200],"kashikabu_zan":[86500,92900],"sashihiki_zan":[-71800,-78700],"yushi_shin":[3800,100],"yushi_hen":[200,600],"kashikabu_shin":[10600,6500],"kashikabu_hen":[0,100]},"8165":{"yushi_zan":[211600,441100],"kashikabu_zan":[415700,414900],"sashihiki_zan":[-204100,26200],"yushi_shin":[170300,399800],"yushi_hen":[400200,170300],"kashikabu_shin":[800,0],"kashikabu_hen":[13000,800]},"8166":{"yushi_zan":[37000,37700],"kashikabu_zan":[0,0],"sashihiki_zan":[37000,37700],"yushi_shin":[0,700],"yushi_hen":[0,0],"kashikabu_shin":[0,0],"kashikabu_hen":[0,0]},"8167":{"yushi_zan":[9800,10000],"kashikabu_zan":[10000,10000],"sashihiki_zan":[-200,0],"yushi_shin":[3100,2500],"yushi_hen":[100,2300],"kashikabu_shin":[500,100],"kashikabu_hen":[100,100]},"8173":{"yushi_zan":[11500,6700],"kashikabu_zan":[62400,61900],"sashihiki_zan":[-50900,-55200],"yushi_shin":[3800,500],"yushi_hen":[0,5300],"kashikabu_shin":[400,100],"kashikabu_hen":[200,600]},"8174":{"yushi_zan":[1200,1000],"kashikabu_zan":[500,500],"sashihiki_zan":[700,500],"yushi_shin":[200,0],"yushi_hen":[0,200],"kashikabu_shin":[0,0],"kashikabu_hen":[100,0]},"8179":{"yushi_zan":[18300,23400],"kashikabu_zan":[48600,48600],"sashihiki_zan":[-30300,-25200],"yushi_shin":[2900,5200],"yushi_hen":[100,100],"kashikabu_shin":[3400,200],"kashikabu_hen":[100,200]},"8181":{"yushi_zan":[600,600],"kashikabu_zan":[0,0],"sashihiki_zan":[600,600],"yushi_shin":[0,0],"yushi_hen":[0,0],"kashikabu_shin":[0,0],"kashikabu_hen":[0,0]},"8185":{"yushi_zan":[54900,49400],"kashikabu_zan":[54900,56200],"sashihiki_zan":[0,-6800],"yushi_shin":[18000,12600],"yushi_hen":[10600,18100],"kashikabu_shin":[1100,1300],"kashikabu_hen":[0,0]},"8194":{"yushi_zan":[21500,22900],"kashikabu_zan":[38900,38800],"sashihiki_zan":[-17400,-15900],"yushi_shin":[1500,2200],"yushi_hen":[0,800],"kashikabu_shin":[4000,100],"kashikabu_hen":[100,200]},"8198":{"yushi_zan":[1600,2300],"kashikabu_zan":[0,0],"sashihiki_zan":[1600,2300],"yushi_shin":[100,700],"yushi_hen":[0,0],"kashikabu_shin":[0,0],"kashikabu_hen":[0,0]}}}